closure/__init__.py
closure/closure.jar
closure-20190417.dist-info/METADATA
closure-20190417.dist-info/WHEEL
closure-20190417.dist-info/entry_points.txt
closure-20190417.dist-info/top_level.txt
closure-20190417.dist-info/RECORD
