Metadata-Version: 1.1
Name: closure
Version: 20190417
Summary: Closure compiler packaged for Python
Home-page: http://pypi.python.org/pypi/closure
Author: Michael Elsdörfer
Author-email: michael@elsdoerfer.com
License: BSD
Platform: UNKNOWN
Classifier: Development Status :: 5 - Production/Stable
Classifier: Environment :: Web Environment
Classifier: License :: OSI Approved :: BSD License
Classifier: Topic :: Internet :: WWW/HTTP :: Site Management
